wizproxy/__init__.py
wizproxy/__main__.py
wizproxy/core/__init__.py
wizproxy/core/parcel.py
wizproxy/core/proxy.py
wizproxy/core/shard.py
wizproxy/crypto/__init__.py
wizproxy/crypto/aes.py
wizproxy/crypto/key_chain.py
wizproxy/plugin/__init__.py
wizproxy/plugin/_filter.py
wizproxy/plugin/builtin.py
wizproxy/plugin/interface.py
wizproxy/plugin/log.py
wizproxy/plugin/scapy.py
wizproxy/proto/__init__.py
wizproxy/proto/addr.py
wizproxy/proto/bytes.py
wizproxy/proto/dml.py
wizproxy/proto/frame.py
wizproxy/proto/handshake.py
wizproxy/session/__init__.py
wizproxy/session/challenges/__init__.py
wizproxy/session/challenges/client_sig.py
wizproxy/session/impl.py
wizproxy/transport/__init__.py
wizproxy/transport/packet_buffer.py
wizproxy/transport/stream.py
wizproxy-0.5.0.dist-info/LICENSE
wizproxy-0.5.0.dist-info/METADATA
wizproxy-0.5.0.dist-info/WHEEL
wizproxy-0.5.0.dist-info/entry_points.txt
wizproxy-0.5.0.dist-info/RECORD
