Metadata-Version: 2.1
Name: wizproxy
Version: 0.5.0
Summary: A proxy for handling encrypted Wizard101 traffic
License: ISC
Author: Valentin B.
Author-email: valentin.be@protonmail.com
Requires-Python: >=3.9,<4.0
Classifier: License :: OSI Approved
Classifier: Programming Language :: Python :: 3
Classifier: Programming Language :: Python :: 3.9
Classifier: Programming Language :: Python :: 3.10
Classifier: Programming Language :: Python :: 3.11
Classifier: Programming Language :: Python :: 3.12
Requires-Dist: click (>=8.1.7,<9.0.0)
Requires-Dist: exceptiongroup (>=1.1.3,<2.0.0)
Requires-Dist: loguru (>=0.7.0,<0.8.0)
Requires-Dist: pycryptodome (>=3.18.0,<4.0.0)
Requires-Dist: scapy (>=2.5.0,<3.0.0)
Requires-Dist: trio (>=0.22.0,<0.23.0)
